wtc/__init__.py
wtc/wtc.py
wtc-1.2.1.dist-info/LICENSE
wtc-1.2.1.dist-info/METADATA
wtc-1.2.1.dist-info/WHEEL
wtc-1.2.1.dist-info/top_level.txt
wtc-1.2.1.dist-info/RECORD
