Metadata-Version: 2.1
Name: wtc
Version: 1.2.1
Summary: Compress osu replay lzma bytestrings
Home-page: https://github.com/circleguard/wtc-lzma-compressor
Author: Chris Miuchiz
Author-email: chrismiuchiz@gmail.com
License: MIT
Download-URL: https://github.com/circleguard/wtc-lzma-compressor/tarball/v1.2.1
Keywords: osu!, compression, lzma, python, replay, osr
Platform: UNKNOWN
Classifier: Programming Language :: Python :: 3
Classifier: License :: OSI Approved :: MIT License
Classifier: Operating System :: OS Independent
